<?xml version="1.0" encoding="UTF-8" standalone="no"?>
<station CODE="LEMB" ELEVATION="229.8" LATITUDE="49.034733" LONGITUDE="7.759407" NAME="Lembach">
    <channel ChannelCode="HHE" Gain="1.0990829111402945E18" LocationCode="00" Network="FR">
        <poles>
            <pole>-0.03691000118851662 0.0370200015604496</pole>
            <pole>-0.03691000118851662 -0.0370200015604496</pole>
            <pole>-343.0 0.0</pole>
            <pole>-370.0 467.0</pole>
            <pole>-370.0 -467.0</pole>
            <pole>-836.0 1522.0</pole>
            <pole>-836.0 -1522.0</pole>
            <pole>-4900.0 4700.0</pole>
            <pole>-4900.0 -4700.0</pole>
            <pole>-6900.0 0.0</pole>
            <pole>-15000.0 0.0</pole>
        </poles>
        <zeroes>
            <zero>0.0 0.0</zero>
            <zero>0.0 0.0</zero>
            <zero>-392.0 0.0</zero>
            <zero>-1960.0 0.0</zero>
            <zero>-1490.0 1740.0</zero>
            <zero>-1490.0 -1740.0</zero>
            <zero>0.0 0.0</zero>
        </zeroes>
    </channel>
    <channel ChannelCode="HHN" Gain="1.098677082770673E18" LocationCode="00" Network="FR">
        <poles>
            <pole>-0.03691000118851662 0.0370200015604496</pole>
            <pole>-0.03691000118851662 -0.0370200015604496</pole>
            <pole>-343.0 0.0</pole>
            <pole>-370.0 467.0</pole>
            <pole>-370.0 -467.0</pole>
            <pole>-836.0 1522.0</pole>
            <pole>-836.0 -1522.0</pole>
            <pole>-4900.0 4700.0</pole>
            <pole>-4900.0 -4700.0</pole>
            <pole>-6900.0 0.0</pole>
            <pole>-15000.0 0.0</pole>
        </poles>
        <zeroes>
            <zero>0.0 0.0</zero>
            <zero>0.0 0.0</zero>
            <zero>-392.0 0.0</zero>
            <zero>-1960.0 0.0</zero>
            <zero>-1490.0 1740.0</zero>
            <zero>-1490.0 -1740.0</zero>
            <zero>0.0 0.0</zero>
        </zeroes>
    </channel>
    <channel ChannelCode="HHZ" Gain="1.0988310761902003E18" LocationCode="00" Network="FR">
        <poles>
            <pole>-0.03691000118851662 0.0370200015604496</pole>
            <pole>-0.03691000118851662 -0.0370200015604496</pole>
            <pole>-343.0 0.0</pole>
            <pole>-370.0 467.0</pole>
            <pole>-370.0 -467.0</pole>
            <pole>-836.0 1522.0</pole>
            <pole>-836.0 -1522.0</pole>
            <pole>-4900.0 4700.0</pole>
            <pole>-4900.0 -4700.0</pole>
            <pole>-6900.0 0.0</pole>
            <pole>-15000.0 0.0</pole>
        </poles>
        <zeroes>
            <zero>0.0 0.0</zero>
            <zero>0.0 0.0</zero>
            <zero>-392.0 0.0</zero>
            <zero>-1960.0 0.0</zero>
            <zero>-1490.0 1740.0</zero>
            <zero>-1490.0 -1740.0</zero>
            <zero>0.0 0.0</zero>
        </zeroes>
    </channel>
    <channel ChannelCode="HNZ" Gain="8.751695622287708E10" LocationCode="01" Network="FR">
        <poles>
            <pole>-155.49400329589844 52.20280075073242</pole>
            <pole>-155.49400329589844 -52.20280075073242</pole>
            <pole>-235.50399780273438 399.7969970703125</pole>
            <pole>-235.50399780273438 -399.7969970703125</pole>
            <pole>-912.9130249023438 784.1799926757812</pole>
            <pole>-912.9130249023438 -784.1799926757812</pole>
        </poles>
        <zeroes>
            <zero>-81.96479797363281 0.0</zero>
            <zero>0.0 0.0</zero>
        </zeroes>
    </channel>
    <channel ChannelCode="HNN" Gain="8.751695622287708E10" LocationCode="01" Network="FR">
        <poles>
            <pole>-155.49400329589844 52.20280075073242</pole>
            <pole>-155.49400329589844 -52.20280075073242</pole>
            <pole>-235.50399780273438 399.7969970703125</pole>
            <pole>-235.50399780273438 -399.7969970703125</pole>
            <pole>-912.9130249023438 784.1799926757812</pole>
            <pole>-912.9130249023438 -784.1799926757812</pole>
        </poles>
        <zeroes>
            <zero>-81.96479797363281 0.0</zero>
            <zero>0.0 0.0</zero>
        </zeroes>
    </channel>
    <channel ChannelCode="HNE" Gain="8.751695622287708E10" LocationCode="01" Network="FR">
        <poles>
            <pole>-155.49400329589844 52.20280075073242</pole>
            <pole>-155.49400329589844 -52.20280075073242</pole>
            <pole>-235.50399780273438 399.7969970703125</pole>
            <pole>-235.50399780273438 -399.7969970703125</pole>
            <pole>-912.9130249023438 784.1799926757812</pole>
            <pole>-912.9130249023438 -784.1799926757812</pole>
        </poles>
        <zeroes>
            <zero>-81.96479797363281 0.0</zero>
            <zero>0.0 0.0</zero>
        </zeroes>
    </channel>
</station>
