<?xml version="1.0" encoding="UTF-8" standalone="no"?>
<station CODE="VEPO" ELEVATION="10.0" LATITUDE="40.8067" LONGITUDE="14.3368" NAME="ENEA Portici - Stazione Osservatorio Vesuviano">
    <channel ChannelCode="HHE" Gain="0.3" LocationCode="" Network="IV">
        <poles>
            <pole>-0.2199999988079071 0.23499999940395355</pole>
            <pole>-0.2199999988079071 -0.23499999940395355</pole>
            <pole>-0.23000000417232513 0.0</pole>
        </poles>
        <zeroes>
            <zero>0.0 0.0</zero>
            <zero>0.0 0.0</zero>
            <zero>0.0 0.0</zero>
            <zero>0.0 0.0</zero>
        </zeroes>
    </channel>
    <channel ChannelCode="HHN" Gain="0.3" LocationCode="" Network="IV">
        <poles>
            <pole>-0.2199999988079071 0.23499999940395355</pole>
            <pole>-0.2199999988079071 -0.23499999940395355</pole>
            <pole>-0.23000000417232513 0.0</pole>
        </poles>
        <zeroes>
            <zero>0.0 0.0</zero>
            <zero>0.0 0.0</zero>
            <zero>0.0 0.0</zero>
            <zero>0.0 0.0</zero>
        </zeroes>
    </channel>
    <channel ChannelCode="HHZ" Gain="0.3" LocationCode="" Network="IV">
        <poles>
            <pole>-0.2199999988079071 0.23499999940395355</pole>
            <pole>-0.2199999988079071 -0.23499999940395355</pole>
            <pole>-0.23000000417232513 0.0</pole>
        </poles>
        <zeroes>
            <zero>0.0 0.0</zero>
            <zero>0.0 0.0</zero>
            <zero>0.0 0.0</zero>
            <zero>0.0 0.0</zero>
        </zeroes>
    </channel>
</station>
